EQViewer/__init__.py
EQViewer/eqviewer.py
EQViewer/utils.py
EQViewer-0.0.2.dist-info/LICENSE
EQViewer-0.0.2.dist-info/METADATA
EQViewer-0.0.2.dist-info/WHEEL
EQViewer-0.0.2.dist-info/top_level.txt
EQViewer-0.0.2.dist-info/RECORD
