Metadata-Version: 2.1
Name: EQViewer
Version: 0.0.2
Summary: Visualize seismicity
Home-page: https://github.com/ecastillot/EQViewer
Author: ecastillot (Emmanuel Castillo)
Author-email: <ecastillot@unal.edu.co>
Keywords: python,eqviewer,earthquakes,seismology
Classifier: Development Status :: 1 - Planning
Classifier: Intended Audience :: Developers
Classifier: Programming Language :: Python :: 3
Classifier: Operating System :: Unix
Requires-Python: >=3.8
License-File: LICENSE
Requires-Dist: pygmt (==0.7.0)
Requires-Dist: geopandas (==0.12.1)
Requires-Dist: openpyxl (==3.0.10)
Requires-Dist: obspy (>=1.3)
Requires-Dist: ipykernel (~=5.3.4)
